hpctestlib/data_analytics/spark/spark_checks.py
hpctestlib/data_analytics/spark/src/spark_pi.py
hpctestlib/interactive/jupyter/ipcmagic/__init__.py
hpctestlib/microbenchmarks/gpu/gpu_burn.py
hpctestlib/microbenchmarks/gpu/dgemm/__init__.py
hpctestlib/microbenchmarks/gpu/kernel_latency/__init__.py
hpctestlib/microbenchmarks/gpu/memory_bandwidth/__init__.py
hpctestlib/microbenchmarks/gpu/pointer_chase/__init__.py
hpctestlib/microbenchmarks/gpu/shmem/__init__.py
hpctestlib/microbenchmarks/mpi/osu.py
hpctestlib/ml/pytorch/horovod.py
hpctestlib/ml/tensorflow/horovod.py
hpctestlib/python/numpy/numpy_ops.py
hpctestlib/python/numpy/src/np_ops.py
hpctestlib/sciapps/amber/nve.py
hpctestlib/sciapps/gromacs/benchmarks.py
hpctestlib/sciapps/metalwalls/benchmarks.py
hpctestlib/sciapps/qespresso/benchmarks.py
hpctestlib/system/fs/mnt_opts.py
hpctestlib/system/ssh/host_keys.py
reframe/__init__.py
reframe/core/backends.py
reframe/core/buildsystems.py
reframe/core/builtins.py
reframe/core/config.py
reframe/core/containers.py
reframe/core/decorators.py
reframe/core/deferrable.py
reframe/core/environments.py
reframe/core/exceptions.py
reframe/core/fields.py
reframe/core/fixtures.py
reframe/core/hooks.py
reframe/core/logging.py
reframe/core/meta.py
reframe/core/modules.py
reframe/core/namespaces.py
reframe/core/parameters.py
reframe/core/pipeline.py
reframe/core/runtime.py
reframe/core/settings.py
reframe/core/shell.py
reframe/core/systems.py
reframe/core/variables.py
reframe/core/warnings.py
reframe/core/launchers/__init__.py
reframe/core/launchers/local.py
reframe/core/launchers/mpi.py
reframe/core/launchers/rsh.py
reframe/core/schedulers/__init__.py
reframe/core/schedulers/flux.py
reframe/core/schedulers/local.py
reframe/core/schedulers/lsf.py
reframe/core/schedulers/oar.py
reframe/core/schedulers/pbs.py
reframe/core/schedulers/registry.py
reframe/core/schedulers/sge.py
reframe/core/schedulers/slurm.py
reframe/core/schedulers/ssh.py
reframe/frontend/__init__.py
reframe_hpc-4.9.1.dist-info/licenses/LICENSE
reframe_hpc-4.9.1.dist-info/METADATA
reframe_hpc-4.9.1.dist-info/WHEEL
reframe_hpc-4.9.1.dist-info/top_level.txt
reframe_hpc-4.9.1.dist-info/RECORD
