Metadata-Version: 2.4
Name: ReFrame-HPC
Version: 4.9.1
Summary: ReFrame is a powerful framework for writing system regression tests and benchmarks, specifically targeted to HPC systems
Home-page: https://github.com/reframe-hpc/reframe
Author: Swiss National Supercomputing Center (CSCS/ETH Zurich), ReFrame Project Developers
License: BSD 3-Clause
Classifier: Development Status :: 5 - Production/Stable
Classifier: Programming Language :: Python :: 3.6
Classifier: Programming Language :: Python :: 3.7
Classifier: Programming Language :: Python :: 3.8
Classifier: Programming Language :: Python :: 3.9
Classifier: Programming Language :: Python :: 3.10
Classifier: Programming Language :: Python :: 3.11
Classifier: Programming Language :: Python :: 3.12
Classifier: Programming Language :: Python :: 3.13
Classifier: License :: OSI Approved :: BSD License
Classifier: Operating System :: MacOS
Classifier: Operating System :: POSIX :: Linux
Classifier: Environment :: Console
Requires-Python: >=3.6
License-File: LICENSE
Requires-Dist: archspec>=0.2.4
Requires-Dist: argcomplete
Requires-Dist: argcomplete<=3.1.2; python_version < "3.8"
Requires-Dist: ClusterShell
Requires-Dist: fasteners==0.19; python_version < "3.10"
Requires-Dist: fasteners
Requires-Dist: jinja2==3.0.3; python_version == "3.6"
Requires-Dist: jinja2
Requires-Dist: jsonschema
Requires-Dist: lxml==5.2.0; python_version < "3.8" and platform_machine == "aarch64"
Requires-Dist: lxml==5.4.0; python_version < "3.8" and platform_machine != "aarch64"
Requires-Dist: lxml
Requires-Dist: PyYAML==6.0.1; python_version < "3.8"
Requires-Dist: PyYAML
Requires-Dist: requests
Requires-Dist: requests<=2.27.1; python_version == "3.6"
Requires-Dist: semver
Requires-Dist: semver<=2.13.0; python_version == "3.6"
Requires-Dist: tabulate
Requires-Dist: tabulate<=0.8.10; python_version == "3.6"
Dynamic: license-file
